pydomainr/__init__.py
pydomainr/PyDomainr.py
pydomainr-1.3.dist-info/DESCRIPTION.rst
pydomainr-1.3.dist-info/METADATA
pydomainr-1.3.dist-info/metadata.json
pydomainr-1.3.dist-info/RECORD
pydomainr-1.3.dist-info/top_level.txt
pydomainr-1.3.dist-info/WHEEL
