Metadata-Version: 2.0
Name: pydomainr
Version: 1.3
Summary: Python wrapper around the domai.nr API
Home-page: http://github.com/itsnauman/PyDomainr
Author: Nauman Ahmad
Author-email: nauman-ahmad@outlook.com
License: MIT
Platform: UNKNOWN
Requires-Dist: requests
